tds_django/__init__.py
tds_django/base.py
tds_django/client.py
tds_django/compiler.py
tds_django/creation.py
tds_django/features.py
tds_django/functions.py
tds_django/introspection.py
tds_django/operations.py
tds_django/patches.py
tds_django/schema.py
tds_django/tz.py
tds_django/validation.py
tds_django/sql/__init__.py
tds_django/sql/clr.sql
tds_django/sql/init.sql
tds_django/sql/queries.py
tds_django-4.2.2.dist-info/LICENSE
tds_django-4.2.2.dist-info/METADATA
tds_django-4.2.2.dist-info/WHEEL
tds_django-4.2.2.dist-info/top_level.txt
tds_django-4.2.2.dist-info/RECORD
