Metadata-Version: 2.1
Name: tds-django
Version: 4.2.2
Summary: Django backend for SQL Server using tds
Home-page: https://github.com/ecogels/tds-django
Author: Etienne Cogels
Author-email: ecogels@users.noreply.github.com
Project-URL: Bug Tracker, https://github.com/ecogels/tds-django/issues
Classifier: Programming Language :: Python :: 3
Classifier: License :: OSI Approved :: BSD License
Classifier: Operating System :: OS Independent
Classifier: Development Status :: 4 - Beta
Classifier: Framework :: Django
Classifier: Framework :: Django :: 3.2
Classifier: Framework :: Django :: 4.0
Classifier: Framework :: Django :: 4.1
Classifier: Framework :: Django :: 4.2
Classifier: Programming Language :: Python
Classifier: Topic :: Database
Classifier: Topic :: Software Development :: Libraries
Requires-Python: >=3.8
License-File: LICENSE
